MANIFEST.in
README.md
pyproject.toml
setup.cfg
setup.py
django_multiple_chunk_upload/__init__.py
django_multiple_chunk_upload/admin.py
django_multiple_chunk_upload/apps.py
django_multiple_chunk_upload/choices.py
django_multiple_chunk_upload/exceptions.py
django_multiple_chunk_upload/mixins.py
django_multiple_chunk_upload/models.py
django_multiple_chunk_upload/tests.py
django_multiple_chunk_upload/views.py
django_multiple_chunk_upload.egg-info/PKG-INFO
django_multiple_chunk_upload.egg-info/SOURCES.txt
django_multiple_chunk_upload.egg-info/dependency_links.txt
django_multiple_chunk_upload.egg-info/requires.txt
django_multiple_chunk_upload.egg-info/top_level.txt
django_multiple_chunk_upload/migrations/__init__.py
django_multiple_chunk_upload/static/django_multiple_chunk_upload/js/chunk_upload.js