Metadata-Version: 1.2
Name: django-multiple-chunk-upload
Version: 1.1
Summary: Chunk upload
Home-page: https://pythonando.com.br
Author: Caio Sampaio
Author-email: caio@pythonando.com.br
License: MIT  # Example license
Platform: UNKNOWN
Requires-Python: >=3.8
